dockreap/__init__.py
dockreap/__main__.py
dockreap-1.0.1.dist-info/licenses/LICENSE
dockreap-1.0.1.dist-info/METADATA
dockreap-1.0.1.dist-info/WHEEL
dockreap-1.0.1.dist-info/entry_points.txt
dockreap-1.0.1.dist-info/top_level.txt
dockreap-1.0.1.dist-info/RECORD
