Metadata-Version: 2.4
Name: dockreap
Version: 1.0.1
Summary: Remove unused anonymous Docker volumes (with symlink cleanup).
Author: Kevin Veen-Birkenbach
License: MIT
Project-URL: Homepage, https://www.veen.world/
Project-URL: Repository, https://github.com/kevinveenbirkenbach/dockreap
Keywords: docker,volumes,cleanup,devops
Classifier: License :: OSI Approved :: MIT License
Classifier: Programming Language :: Python :: 3
Classifier: Programming Language :: Python :: 3 :: Only
Classifier: Environment :: Console
Classifier: Operating System :: POSIX :: Linux
Classifier: Topic :: System :: Systems Administration
Requires-Python: >=3.9
License-File: LICENSE
Dynamic: license-file
